classifaier/__init__.py
classifaier/classifaier.py
tests/__init__.py
tests/test_classifier.py
ClassifAIer-0.1.6.dist-info/LICENSE
ClassifAIer-0.1.6.dist-info/METADATA
ClassifAIer-0.1.6.dist-info/WHEEL
ClassifAIer-0.1.6.dist-info/top_level.txt
ClassifAIer-0.1.6.dist-info/RECORD
