Metadata-Version: 2.1
Name: ClassifAIer
Version: 0.1.6
Summary: A library for text classification using LangChain embeddings and scikit-learn classifiers.
Home-page: https://github.com/AimTune/ClassifAIer
Author: Hamza Agar
Author-email: hamzaagareng@gmail.com
Classifier: Programming Language :: Python :: 3
Classifier: License :: OSI Approved :: MIT License
Classifier: Operating System :: OS Independent
Requires-Python: >=3.7
License-File: LICENSE
Requires-Dist: scikit-learn
Requires-Dist: langchain-core
Requires-Dist: langchain
Requires-Dist: numpy
